HandDectector/HandDetector.py
HandDectector/__init__.py
HandDectector-0.1.dist-info/LICENSE
HandDectector-0.1.dist-info/METADATA
HandDectector-0.1.dist-info/WHEEL
HandDectector-0.1.dist-info/top_level.txt
HandDectector-0.1.dist-info/RECORD
